SpeechToText/main.py
Sakesama-0.1.dist-info/METADATA
Sakesama-0.1.dist-info/WHEEL
Sakesama-0.1.dist-info/top_level.txt
Sakesama-0.1.dist-info/RECORD
