Metadata-Version: 2.1
Name: Sakesama
Version: 0.1
Summary: This is a speech to text package created by your Kaijakuri
Author-email: pr4een3@gmail.com
